MANIFEST.in
README.md
setup.py
cbpi4ui/__init__.py
cbpi4ui/config.yaml
cbpi4ui/version.py
cbpi4ui.egg-info/PKG-INFO
cbpi4ui.egg-info/SOURCES.txt
cbpi4ui.egg-info/dependency_links.txt
cbpi4ui.egg-info/top_level.txt
cbpi4ui/build/.DS_Store
cbpi4ui/build/asset-manifest.json
cbpi4ui/build/favicon.ico
cbpi4ui/build/index.html
cbpi4ui/build/logo192.png
cbpi4ui/build/logo512.png
cbpi4ui/build/manifest.json
cbpi4ui/build/paypal.png
cbpi4ui/build/robots.txt
cbpi4ui/build/static/css/main.c53dbdb4.chunk.css
cbpi4ui/build/static/css/main.c53dbdb4.chunk.css.map
cbpi4ui/build/static/js/2.d09ba6ad.chunk.js
cbpi4ui/build/static/js/2.d09ba6ad.chunk.js.LICENSE.txt
cbpi4ui/build/static/js/2.d09ba6ad.chunk.js.map
cbpi4ui/build/static/js/3.76c38f25.chunk.js
cbpi4ui/build/static/js/3.76c38f25.chunk.js.map
cbpi4ui/build/static/js/main.1c810c72.chunk.js
cbpi4ui/build/static/js/main.1c810c72.chunk.js.map
cbpi4ui/build/static/js/runtime-main.dd27fd9f.js
cbpi4ui/build/static/js/runtime-main.dd27fd9f.js.map
cbpi4ui/build/static/media/CBPi_logo.2fc3a7bc.svg
cbpi4ui/build/static/media/cbpi.f1a4ae59.png
cbpi4ui/build/static/media/cbpi_no_border.5446caa7.png
cbpi4ui/build/static/media/cbpi_pattern.ec6e8cb2.png
cbpi4ui/build/static/media/kettle.77e9dd64.svg
cbpi4ui/build/static/media/paypal.86be4c59.png
cbpi4ui/build/static/media/tank2.891ce170.svg