Metadata-Version: 1.0
Name: cbpi4ui
Version: 0.0.9
Summary: CraftBeerPi User Interface
Home-page: http://web.craftbeerpi.com
Author: Manuel Fritsch
Author-email: manuel@craftbeerpi.com
License: UNKNOWN
Platform: UNKNOWN
